Metadata-Version: 1.1
Name: dayli-client
Version: 2.1
Summary: API Client para facturación electrónica
Home-page: https://daylisoft.com.ec/
Author: Daylisoft
Author-email: daylisoft@gmail.com
License: MIT
Keywords: facturacion,client,daylisoft,sri,electronica
Platform: UNKNOWN
Classifier: Development Status :: 3 - Alpha
Classifier: Intended Audience :: Developers
Classifier: Topic :: Software Development :: Build Tools
Classifier: Programming Language :: Python :: 2.7
